sqlalchemy_dhis2/__init__.py
sqlalchemy_dhis2/array.py
sqlalchemy_dhis2/config.py
sqlalchemy_dhis2/connection.py
sqlalchemy_dhis2/constants.py
sqlalchemy_dhis2/datatypes.py
sqlalchemy_dhis2/exceptions.py
sqlalchemy_dhis2/jsonhttp_dialect.py
sqlalchemy_dhis2/message_formatter.py
sqlalchemy_dhis2/polars_extensions.py
sqlalchemy_dhis2/sql_extensions.py
sqlalchemy_dhis2/supports.py
sqlalchemy_dhis2/table_reflect.py
sqlalchemy_dhis2/type_map.py
sqlalchemydhis2-1.0.71.dist-info/LICENSE
sqlalchemydhis2-1.0.71.dist-info/METADATA
sqlalchemydhis2-1.0.71.dist-info/WHEEL
sqlalchemydhis2-1.0.71.dist-info/entry_points.txt
sqlalchemydhis2-1.0.71.dist-info/top_level.txt
sqlalchemydhis2-1.0.71.dist-info/RECORD
